kcanal/__init__.py
kcanal/circuit.py
kcanal/cyclone.py
kcanal/interconnect.py
kcanal/logic.py
kcanal/pnr.py
kcanal/tester.py
kcanal/util.py
kcanal-0.0.1.dist-info/LICENSE
kcanal-0.0.1.dist-info/METADATA
kcanal-0.0.1.dist-info/WHEEL
kcanal-0.0.1.dist-info/top_level.txt
kcanal-0.0.1.dist-info/RECORD
