Metadata-Version: 2.1
Name: kcanal
Version: 0.0.1
Summary: UNKNOWN
Home-page: https://github.com/Kuree/kcanal
Author: Keyi Zhang
Author-email: keyi@cs.stanford.edu
License: UNKNOWN
Platform: UNKNOWN
Requires-Python: >=3.6
License-File: LICENSE
Requires-Dist: kratos
Provides-Extra: test
Requires-Dist: archipelago ; extra == 'test'
Requires-Dist: pytest ; extra == 'test'
